[{"target_asn":37468,"name":"ANGOLA-CABLES","customer_cones":22,"num_peers":0},{"target_asn":328509,"name":"SpeedNet-Servicos","customer_cones":0,"num_peers":0},{"target_asn":37119,"name":"unitel-AS","customer_cones":8,"num_peers":0},{"target_asn":11259,"name":"ANGOLATELECOM","customer_cones":11,"num_peers":0},{"target_asn":37272,"name":"CMCANGOLA","customer_cones":0,"num_peers":0},{"target_asn":36917,"name":"ACS","customer_cones":2,"num_peers":0},{"target_asn":328111,"name":"IPWORLD-AS","customer_cones":2,"num_peers":0},{"target_asn":328154,"name":"NETSPACE","customer_cones":5,"num_peers":0},{"target_asn":36976,"name":"SONANGOL","customer_cones":0,"num_peers":0},{"target_asn":17400,"name":"EBONET","customer_cones":3,"num_peers":0},{"target_asn":328718,"name":"ANYCONNECT","customer_cones":0,"num_peers":0},{"target_asn":36907,"name":"TVCaboAngola","customer_cones":6,"num_peers":0},{"target_asn":327801,"name":"Banco-Sol","customer_cones":0,"num_peers":0},{"target_asn":37593,"name":"Infrasat","customer_cones":0,"num_peers":0},{"target_asn":327932,"name":"CONNECTIS-DATA-ANGOLA","customer_cones":6,"num_peers":0},{"target_asn":37645,"name":"ZAP-Angola","customer_cones":0,"num_peers":0},{"target_asn":32717,"name":"ASN-SNETANGOLA","customer_cones":0,"num_peers":0},{"target_asn":328877,"name":"Banco-Valor-AS","customer_cones":0,"num_peers":0},{"target_asn":328792,"name":"EEID-AS","customer_cones":0,"num_peers":0},{"target_asn":36881,"name":"MULTITEL","customer_cones":0,"num_peers":0},{"target_asn":36936,"name":"BancoBai","customer_cones":0,"num_peers":0},{"target_asn":327918,"name":"AEID","customer_cones":0,"num_peers":0},{"target_asn":37264,"name":"DNSANGOLA","customer_cones":0,"num_peers":0},{"target_asn":327691,"name":"BMAS-AS","customer_cones":0,"num_peers":0},{"target_asn":37062,"name":"ASN-BNI","customer_cones":0,"num_peers":0},{"target_asn":37081,"name":"movicel-as","customer_cones":0,"num_peers":0},{"target_asn":328669,"name":"BOLSA-DE-DIVIDA","customer_cones":0,"num_peers":0},{"target_asn":37011,"name":"MSTARTEL-AS","customer_cones":0,"num_peers":0},{"target_asn":328943,"name":"AAS1-AS","customer_cones":0,"num_peers":0},{"target_asn":328211,"name":"SETIC-FP-AS","customer_cones":0,"num_peers":0},{"target_asn":328907,"name":"AS33793","customer_cones":0,"num_peers":0},{"target_asn":37603,"name":"GameZone-AS","customer_cones":0,"num_peers":0},{"target_asn":328295,"name":"BANCO-AS","customer_cones":0,"num_peers":0},{"target_asn":37318,"name":"BESA","customer_cones":0,"num_peers":0},{"target_asn":327806,"name":"CNTI-AS","customer_cones":0,"num_peers":0},{"target_asn":328725,"name":"Advanlink-AS","customer_cones":0,"num_peers":0},{"target_asn":328893,"name":"KWATTEL-AS","customer_cones":0,"num_peers":0},{"target_asn":37036,"name":"BFA","customer_cones":0,"num_peers":0},{"target_asn":327775,"name":"AO-IXPmgmnt","customer_cones":0,"num_peers":0},{"target_asn":37267,"name":"CAIXA","customer_cones":0,"num_peers":0},{"target_asn":329011,"name":"Multipla-AS","customer_cones":0,"num_peers":0},{"target_asn":327833,"name":"CENTRAL-8","customer_cones":0,"num_peers":0},{"target_asn":37366,"name":"BNA","customer_cones":0,"num_peers":0},{"target_asn":37384,"name":"BANKO-KEVE","customer_cones":0,"num_peers":0},{"target_asn":328273,"name":"BCS-Banco-de-Credito-do-Sul-SA","customer_cones":0,"num_peers":0},{"target_asn":329194,"name":"Banco-De-Comercio-e-Industria-SA","customer_cones":0,"num_peers":0},{"target_asn":328165,"name":"Banco-de-Investimento-Rural","customer_cones":0,"num_peers":0},{"target_asn":329108,"name":"LCL3-AS","customer_cones":0,"num_peers":0},{"target_asn":37590,"name":"BCA-ASN","customer_cones":0,"num_peers":0},{"target_asn":329210,"name":"HSTL1-AS","customer_cones":0,"num_peers":0},{"target_asn":328283,"name":"BBDP1-AS","customer_cones":0,"num_peers":0},{"target_asn":329065,"name":"STSL2-AS","customer_cones":0,"num_peers":0},{"target_asn":37147,"name":"bancobic-as","customer_cones":0,"num_peers":0},{"target_asn":328979,"name":"NPDS-AS","customer_cones":0,"num_peers":0}]