[{"target_asn":37196,"name":"SUDATEL-SENEGAL","customer_cones":1,"num_peers":0},{"target_asn":37649,"name":"Tigo","customer_cones":0,"num_peers":0},{"target_asn":37288,"name":"WACREN","customer_cones":0,"num_peers":0},{"target_asn":327809,"name":"ARC-Informatique","customer_cones":0,"num_peers":0},{"target_asn":328558,"name":"Senelec-AS","customer_cones":0,"num_peers":0},{"target_asn":328148,"name":"ADIE-AS","customer_cones":1,"num_peers":0},{"target_asn":328147,"name":"SENIX-MGMT-AS","customer_cones":0,"num_peers":0},{"target_asn":328650,"name":"Universite-Virtuelle-du-Senegal-AS","customer_cones":0,"num_peers":0},{"target_asn":329161,"name":"ATS6-AS","customer_cones":0,"num_peers":0}]