[{"target_asn":37282,"name":"MAINONE","customer_cones":67,"num_peers":0},{"target_asn":29091,"name":"IPNXng","customer_cones":12,"num_peers":1},{"target_asn":37004,"name":"Suburban-Broadband-AS","customer_cones":1,"num_peers":0},{"target_asn":327953,"name":"ABUJA-ELECTRIC","customer_cones":0,"num_peers":0},{"target_asn":37148,"name":"globacom-as","customer_cones":32,"num_peers":0},{"target_asn":37018,"name":"GALAXYBB-AS","customer_cones":2,"num_peers":0},{"target_asn":37605,"name":"GTNL1-AS","customer_cones":0,"num_peers":0},{"target_asn":36911,"name":"DOPC-AS-US","customer_cones":0,"num_peers":0},{"target_asn":37088,"name":"VDT-AS","customer_cones":5,"num_peers":0},{"target_asn":37688,"name":"BCNL1-AS","customer_cones":2,"num_peers":0},{"target_asn":37286,"name":"NG-ICT-FORUM","customer_cones":0,"num_peers":0},{"target_asn":30988,"name":"ISInternetSolutions","customer_cones":6,"num_peers":0},{"target_asn":328457,"name":"Brainshare-Technologies-AS","customer_cones":0,"num_peers":0},{"target_asn":36940,"name":"IXPN-AS-MGMT","customer_cones":6,"num_peers":5},{"target_asn":37340,"name":"Spectranet","customer_cones":0,"num_peers":1},{"target_asn":36873,"name":"VNL1-AS","customer_cones":25,"num_peers":0},{"target_asn":37565,"name":"NSE-AS","customer_cones":0,"num_peers":0},{"target_asn":29465,"name":"VCG-AS","customer_cones":30,"num_peers":2},{"target_asn":37480,"name":"Cobranet","customer_cones":2,"num_peers":0},{"target_asn":329142,"name":"IISL1-AS","customer_cones":0,"num_peers":0},{"target_asn":37629,"name":"eStreamNetworks-AS","customer_cones":0,"num_peers":0},{"target_asn":35074,"name":"AS-COBRANETNG","customer_cones":0,"num_peers":0},{"target_asn":37200,"name":"SIMBANET-NIGERIA","customer_cones":0,"num_peers":0},{"target_asn":37248,"name":"PHASE3TEL","customer_cones":1,"num_peers":0},{"target_asn":30998,"name":"NAL-AS","customer_cones":3,"num_peers":0},{"target_asn":328766,"name":"Hoop-Telecoms-AS","customer_cones":2,"num_peers":0},{"target_asn":327952,"name":"AS-NATCOM","customer_cones":2,"num_peers":0},{"target_asn":329050,"name":"JBNP1-AS","customer_cones":0,"num_peers":0},{"target_asn":37714,"name":"BITFLUX","customer_cones":0,"num_peers":2},{"target_asn":37659,"name":"BillyRonks-Global-AS","customer_cones":0,"num_peers":0},{"target_asn":37209,"name":"HYPERIA","customer_cones":1,"num_peers":1},{"target_asn":327891,"name":"NANOCOM","customer_cones":0,"num_peers":0},{"target_asn":328779,"name":"Proline-Technologies","customer_cones":0,"num_peers":0},{"target_asn":16284,"name":"Inq-Digital-Nigeria-AS","customer_cones":14,"num_peers":0},{"target_asn":37377,"name":"Futurecom","customer_cones":0,"num_peers":0},{"target_asn":328528,"name":"NetIT-Solutions","customer_cones":0,"num_peers":0},{"target_asn":37170,"name":"UNILAG","customer_cones":0,"num_peers":0},{"target_asn":36920,"name":"KKON","customer_cones":4,"num_peers":1},{"target_asn":37076,"name":"EMTS-NIGERIA-AS","customer_cones":2,"num_peers":0},{"target_asn":328160,"name":"Dotmac-Tech","customer_cones":6,"num_peers":0},{"target_asn":37345,"name":"MEDAILLON","customer_cones":0,"num_peers":0},{"target_asn":328503,"name":"Living-Faith-Church-WorldWide-AS","customer_cones":0,"num_peers":0},{"target_asn":328527,"name":"PDS-NETWORKS","customer_cones":1,"num_peers":0},{"target_asn":328999,"name":"BrowsePoint","customer_cones":0,"num_peers":0},{"target_asn":25163,"name":"NG-NIGERIA-AS","customer_cones":2,"num_peers":0},{"target_asn":37682,"name":"TIZETI-AS","customer_cones":0,"num_peers":0},{"target_asn":37405,"name":"UNIV-NG-NSUKKA","customer_cones":0,"num_peers":0},{"target_asn":37308,"name":"COOLLINK","customer_cones":1,"num_peers":0},{"target_asn":37269,"name":"ICSL","customer_cones":0,"num_peers":0},{"target_asn":329191,"name":"NTL3-AS","customer_cones":0,"num_peers":0},{"target_asn":37106,"name":"ODUA-AS","customer_cones":0,"num_peers":0},{"target_asn":328451,"name":"IP-Express-Ltd-AS","customer_cones":0,"num_peers":0},{"target_asn":328401,"name":"SoftAlliance-AS","customer_cones":0,"num_peers":0},{"target_asn":36923,"name":"SWIFTNG-ASN","customer_cones":3,"num_peers":0},{"target_asn":329024,"name":"LFCS1-AS","customer_cones":0,"num_peers":0},{"target_asn":37230,"name":"SWIFTTALK","customer_cones":0,"num_peers":0},{"target_asn":328668,"name":"Nkponani-AS","customer_cones":0,"num_peers":0},{"target_asn":327942,"name":"LANDMARK-UNIVERSITY","customer_cones":0,"num_peers":0},{"target_asn":36993,"name":"FCMB","customer_cones":0,"num_peers":0},{"target_asn":37347,"name":"NGCOM","customer_cones":0,"num_peers":0},{"target_asn":328387,"name":"COZ-Internet-AS","customer_cones":0,"num_peers":0},{"target_asn":37637,"name":"Smile-Nigeria-AS","customer_cones":0,"num_peers":0},{"target_asn":36932,"name":"IXPN-AS","customer_cones":3,"num_peers":0},{"target_asn":328630,"name":"TIZETI_GH","customer_cones":0,"num_peers":0},{"target_asn":37587,"name":"Union-Bank","customer_cones":0,"num_peers":0},{"target_asn":37472,"name":"NIGCOMSAT","customer_cones":0,"num_peers":0},{"target_asn":328309,"name":"Globacom-AS","customer_cones":0,"num_peers":0},{"target_asn":37398,"name":"junisat","customer_cones":0,"num_peers":0},{"target_asn":329054,"name":"PSBL1-AS","customer_cones":0,"num_peers":0},{"target_asn":37025,"name":"BANKPHB","customer_cones":0,"num_peers":0},{"target_asn":328128,"name":"Tehilah-Base-AS","customer_cones":0,"num_peers":0},{"target_asn":328861,"name":"NIMC-AS","customer_cones":0,"num_peers":0},{"target_asn":327985,"name":"IDS-AFRICA","customer_cones":0,"num_peers":0},{"target_asn":328580,"name":"Oplay-Digital-Services","customer_cones":0,"num_peers":0},{"target_asn":328376,"name":"Alfa-O-AS","customer_cones":0,"num_peers":0},{"target_asn":37280,"name":"BCL","customer_cones":1,"num_peers":0},{"target_asn":37521,"name":"Internet-Solutions-","customer_cones":0,"num_peers":0},{"target_asn":37420,"name":"UNIV-JOS","customer_cones":0,"num_peers":0},{"target_asn":328617,"name":"Skystar-Global-Solutions","customer_cones":0,"num_peers":0},{"target_asn":328256,"name":"Skymax-Integrated-Network-AS","customer_cones":0,"num_peers":0},{"target_asn":37125,"name":"Layer3-","customer_cones":2,"num_peers":0},{"target_asn":37077,"name":"AAUN-","customer_cones":0,"num_peers":0},{"target_asn":328497,"name":"Ibadan-Electricity-AS","customer_cones":0,"num_peers":0},{"target_asn":328780,"name":"Imbil-Telecom-AS","customer_cones":0,"num_peers":1},{"target_asn":37452,"name":"CB-Nigeria","customer_cones":0,"num_peers":1},{"target_asn":328189,"name":"ECOBANK-NIGERIA","customer_cones":0,"num_peers":0},{"target_asn":328203,"name":"Platinum-Index-AS","customer_cones":0,"num_peers":0},{"target_asn":328447,"name":"EKO-Electricity-AS","customer_cones":0,"num_peers":0},{"target_asn":37104,"name":"stanbic-as","customer_cones":0,"num_peers":0},{"target_asn":328556,"name":"SYSCODES-COMMUNICATIONS-AS","customer_cones":0,"num_peers":0},{"target_asn":328825,"name":"AACL-AS","customer_cones":0,"num_peers":0},{"target_asn":36922,"name":"UBA-AS","customer_cones":0,"num_peers":0},{"target_asn":37661,"name":"NRaE1-AS","customer_cones":1,"num_peers":1},{"target_asn":328555,"name":"Timeless-Network-Services-AS","customer_cones":0,"num_peers":0},{"target_asn":37588,"name":"ORLEAN-INVEST-AFRICA-LIMITED","customer_cones":0,"num_peers":0},{"target_asn":327705,"name":"FUTA","customer_cones":0,"num_peers":0},{"target_asn":328658,"name":"De-Choicetech-Integrated","customer_cones":1,"num_peers":0},{"target_asn":37192,"name":"ECNX","customer_cones":1,"num_peers":0},{"target_asn":328585,"name":"MegaMore","customer_cones":1,"num_peers":0},{"target_asn":328035,"name":"Zeta-Web-Nigeria-AS","customer_cones":0,"num_peers":0},{"target_asn":327898,"name":"CBC-EMEA","customer_cones":1,"num_peers":0},{"target_asn":328875,"name":"Upperling-AS","customer_cones":0,"num_peers":0},{"target_asn":328696,"name":"Tecpoint-Global-Solutions","customer_cones":0,"num_peers":0},{"target_asn":36938,"name":"NIRA","customer_cones":0,"num_peers":0},{"target_asn":328722,"name":"Ciudad-AS","customer_cones":0,"num_peers":0},{"target_asn":327895,"name":"MEGAFAST-NETWORKS","customer_cones":0,"num_peers":0},{"target_asn":328496,"name":"CyberSOC-Africa-AS","customer_cones":0,"num_peers":0},{"target_asn":37001,"name":"GTB-AS","customer_cones":0,"num_peers":0},{"target_asn":37249,"name":"CWHOUSE","customer_cones":0,"num_peers":0},{"target_asn":36872,"name":"IDN","customer_cones":0,"num_peers":0},{"target_asn":327986,"name":"GUTTI-GLOBAL-NETWORKS","customer_cones":0,"num_peers":0},{"target_asn":37222,"name":"INTERCONNECT-","customer_cones":0,"num_peers":0},{"target_asn":328881,"name":"PEFB-AS","customer_cones":0,"num_peers":0},{"target_asn":328932,"name":"FTNL-AS","customer_cones":0,"num_peers":0},{"target_asn":37296,"name":"AFCOMSAT","customer_cones":0,"num_peers":0},{"target_asn":328940,"name":"VCL8-AS","customer_cones":0,"num_peers":1},{"target_asn":328171,"name":"TREFOIL","customer_cones":0,"num_peers":0},{"target_asn":327721,"name":"Interswitch","customer_cones":0,"num_peers":0},{"target_asn":328852,"name":"Briech-as","customer_cones":0,"num_peers":0},{"target_asn":37056,"name":"ZENITH-BANK","customer_cones":0,"num_peers":0},{"target_asn":328413,"name":"Comercio-Cloud-Computing-Ltd","customer_cones":0,"num_peers":0},{"target_asn":37445,"name":"ETRANZACT","customer_cones":0,"num_peers":0},{"target_asn":329022,"name":"GWNL1-AS","customer_cones":0,"num_peers":0},{"target_asn":37528,"name":"AISA","customer_cones":0,"num_peers":0},{"target_asn":328854,"name":"CEFLIXAS","customer_cones":0,"num_peers":0},{"target_asn":328938,"name":"TMSL1-AS","customer_cones":0,"num_peers":0},{"target_asn":328564,"name":"Informacial-Media-International-AS","customer_cones":0,"num_peers":0},{"target_asn":328945,"name":"NSL7-AS","customer_cones":1,"num_peers":0},{"target_asn":327784,"name":"FIDELITY-BANK","customer_cones":0,"num_peers":0},{"target_asn":36957,"name":"MICROACCESS","customer_cones":0,"num_peers":0},{"target_asn":37522,"name":"Flourmills-","customer_cones":0,"num_peers":0},{"target_asn":328951,"name":"PBL2-AS","customer_cones":0,"num_peers":0},{"target_asn":329083,"name":"WTSO1-AS","customer_cones":0,"num_peers":0},{"target_asn":329051,"name":"Spectranet-Limited","customer_cones":0,"num_peers":0},{"target_asn":327763,"name":"Bowen-University","customer_cones":0,"num_peers":0},{"target_asn":37144,"name":"VALUCARD-","customer_cones":0,"num_peers":0},{"target_asn":329171,"name":"WNL3-AS","customer_cones":0,"num_peers":0},{"target_asn":328742,"name":"Simplifyd-Systems-AS","customer_cones":0,"num_peers":0},{"target_asn":328053,"name":"Sterling-Bank-AS","customer_cones":0,"num_peers":0},{"target_asn":329127,"name":"CSCL1-AS","customer_cones":0,"num_peers":0},{"target_asn":329123,"name":"RPNL1-AS","customer_cones":0,"num_peers":0},{"target_asn":37058,"name":"SKYE-BANK","customer_cones":0,"num_peers":0},{"target_asn":37443,"name":"Usmanu","customer_cones":0,"num_peers":0},{"target_asn":327981,"name":"Ekovolt-Telco","customer_cones":0,"num_peers":0},{"target_asn":37567,"name":"NIBSS","customer_cones":0,"num_peers":0},{"target_asn":37657,"name":"LASG-AS","customer_cones":0,"num_peers":0},{"target_asn":328613,"name":"TRAKATEL","customer_cones":0,"num_peers":0},{"target_asn":328027,"name":"Sahara-Group","customer_cones":0,"num_peers":0},{"target_asn":328823,"name":"JAIZ-AS","customer_cones":0,"num_peers":0},{"target_asn":37433,"name":"KKON-ABUJA","customer_cones":0,"num_peers":0},{"target_asn":37686,"name":"ABUZ1-AS","customer_cones":0,"num_peers":0},{"target_asn":328188,"name":"Covenant-University-AS","customer_cones":0,"num_peers":0},{"target_asn":327843,"name":"PAN-ATLANTIC-UNIVERSITY","customer_cones":0,"num_peers":0},{"target_asn":36970,"name":"interswitch","customer_cones":0,"num_peers":0},{"target_asn":37660,"name":"Premierlotto-AS","customer_cones":0,"num_peers":0},{"target_asn":328971,"name":"MTIL1-AS","customer_cones":0,"num_peers":0},{"target_asn":37426,"name":"Amcon","customer_cones":0,"num_peers":0},{"target_asn":328080,"name":"Inview-Tech-AS","customer_cones":0,"num_peers":0},{"target_asn":328746,"name":"Globus-Bank-AS","customer_cones":0,"num_peers":0},{"target_asn":37194,"name":"VOIX-NETWORKS","customer_cones":0,"num_peers":0},{"target_asn":328175,"name":"Xpress-Payment","customer_cones":0,"num_peers":0},{"target_asn":329182,"name":"AMICS-TECHNOLOGIES-LIMITED","customer_cones":0,"num_peers":0},{"target_asn":328158,"name":"Exchange-Telecoms-Limited","customer_cones":0,"num_peers":0},{"target_asn":328081,"name":"HollaTags-AS","customer_cones":0,"num_peers":0},{"target_asn":327803,"name":"COSCHARIS-TECHNOLOGIES","customer_cones":0,"num_peers":0},{"target_asn":328789,"name":"MCL","customer_cones":0,"num_peers":0},{"target_asn":329023,"name":"Treten-Networks-AS","customer_cones":0,"num_peers":0},{"target_asn":328609,"name":"Axa-Mansard","customer_cones":0,"num_peers":0},{"target_asn":328131,"name":"Webb-Fontaine-AS","customer_cones":0,"num_peers":0},{"target_asn":328305,"name":"Yappingo-AS","customer_cones":0,"num_peers":0},{"target_asn":328332,"name":"FEAP-AS","customer_cones":0,"num_peers":0},{"target_asn":329057,"name":"SCTC1","customer_cones":0,"num_peers":0},{"target_asn":328240,"name":"DANGOTE-AS","customer_cones":0,"num_peers":0},{"target_asn":37328,"name":"WEMABANK","customer_cones":0,"num_peers":0},{"target_asn":328918,"name":"FISL-AS","customer_cones":0,"num_peers":0},{"target_asn":37495,"name":"Eko-Konnect","customer_cones":0,"num_peers":0},{"target_asn":329019,"name":"TLIL1-AS","customer_cones":0,"num_peers":0},{"target_asn":329100,"name":"NUON1-AS","customer_cones":0,"num_peers":0},{"target_asn":329215,"name":"LL4-AS","customer_cones":0,"num_peers":0},{"target_asn":37207,"name":"NNPC","customer_cones":0,"num_peers":0},{"target_asn":328516,"name":"Premium-Pension-Limited-AS","customer_cones":0,"num_peers":0},{"target_asn":328221,"name":"CORALPAY","customer_cones":0,"num_peers":0},{"target_asn":328362,"name":"UniversityIlorin-AS","customer_cones":0,"num_peers":0},{"target_asn":328873,"name":"NationalAssemblyAbuja","customer_cones":0,"num_peers":0},{"target_asn":37540,"name":"WINROCK-","customer_cones":1,"num_peers":0},{"target_asn":329052,"name":"NEDL1-AS","customer_cones":1,"num_peers":1},{"target_asn":328419,"name":"Bayero-University-AS","customer_cones":0,"num_peers":0},{"target_asn":327729,"name":"BABCOCK-UNIV","customer_cones":0,"num_peers":0},{"target_asn":37687,"name":"PAU-AS","customer_cones":0,"num_peers":0},{"target_asn":328522,"name":"Cynox-IT","customer_cones":0,"num_peers":0},{"target_asn":37506,"name":"Zinox","customer_cones":0,"num_peers":0},{"target_asn":328324,"name":"FederalUniversity-AS","customer_cones":0,"num_peers":0},{"target_asn":329031,"name":"RISL1-AS","customer_cones":0,"num_peers":0},{"target_asn":329230,"name":"Pronto-Broadband-Solutions","customer_cones":0,"num_peers":0},{"target_asn":329235,"name":"REXIFI-TECHNOLOGIES-AS","customer_cones":0,"num_peers":0},{"target_asn":328177,"name":"UNI-ABUJA","customer_cones":0,"num_peers":0}]